concierge_mako/__init__.py
concierge_mako/templater.py
concierge_mako-0.2.0.dist-info/DESCRIPTION.rst
concierge_mako-0.2.0.dist-info/METADATA
concierge_mako-0.2.0.dist-info/RECORD
concierge_mako-0.2.0.dist-info/WHEEL
concierge_mako-0.2.0.dist-info/entry_points.txt
concierge_mako-0.2.0.dist-info/metadata.json
concierge_mako-0.2.0.dist-info/pbr.json
concierge_mako-0.2.0.dist-info/top_level.txt
