Metadata-Version: 2.0
Name: concierge-mako
Version: 0.2.0
Summary: Mako templating for concierge
Home-page: https://github.com/9seconds/concierge-mako
Author: Sergey Arkhipov
Author-email: serge@aerialsounds.org
License: MIT
Platform: UNKNOWN
Classifier: Intended Audience :: Information Technology
Classifier: Intended Audience :: System Administrators
Classifier: Operating System :: POSIX :: Linux
Classifier: Programming Language :: Python
Classifier: Programming Language :: Python :: 3
Classifier: Programming Language :: Python :: 3.4
Classifier: Programming Language :: Python :: 3.5
Requires-Dist: concierge (>=0.2,<1.0)
Requires-Dist: mako (>=1.0)
